st_scrapers-0.1.0.dist-info/licenses/LICENSE
stscrapers/__init__.py
stscrapers/scrapers/__init__.py
stscrapers/scrapers/base.py
stscrapers/scrapers/manager.py
stscrapers/scrapers/models.py
stscrapers/scrapers/logs/__init__.py
stscrapers/scrapers/logs/metadata.py
stscrapers/scrapers/socrata/__init__.py
stscrapers/scrapers/socrata/scraper.py
stscrapers/storage/__init__.py
stscrapers/storage/backends.py
stscrapers/transformer/__init__.py
stscrapers/transformer/beam_pipeline.py
stscrapers/transformer/config.py
stscrapers/transformer/transforms/__init__.py
stscrapers/transformer/transforms/sample.py
st_scrapers-0.1.0.dist-info/METADATA
st_scrapers-0.1.0.dist-info/WHEEL
st_scrapers-0.1.0.dist-info/entry_points.txt
st_scrapers-0.1.0.dist-info/top_level.txt
st_scrapers-0.1.0.dist-info/RECORD
