Metadata-Version: 2.4
Name: st-scrapers
Version: 0.1.0
Summary: Scraper and transformer utilities for Subsidy Tracker data ingestion.
Author: Good Jobs First
License:                                  Apache License
Keywords: socrata,sot-scrapers,apache-beam,dataflow
Classifier: Programming Language :: Python :: 3
Classifier: License :: OSI Approved :: MIT License
Classifier: Operating System :: OS Independent
Requires-Python: >=3.10
License-File: LICENSE
Requires-Dist: apache-beam[gcp]>=2.56.0
Requires-Dist: pyyaml>=6.0
Requires-Dist: opynrefine
Provides-Extra: dev
Requires-Dist: pytest>=7.0; extra == "dev"
Dynamic: license-file
